zato_vault_client-1.4-py2.7-nspkg.pth
zato/vault/__init__.py
zato/vault/client.py
zato_vault_client-1.4.dist-info/METADATA
zato_vault_client-1.4.dist-info/WHEEL
zato_vault_client-1.4.dist-info/namespace_packages.txt
zato_vault_client-1.4.dist-info/top_level.txt
zato_vault_client-1.4.dist-info/RECORD
